{
  "project_info": {
    "project_number": "410309064043",
    "project_id": "workwell-f3985",
    "storage_bucket": "workwell-f3985.firebasestorage.app"
  },
  "client": [
    {
      "client_info": {
        "mobilesdk_app_id": "1:410309064043:android:c91ca4e3a59c11477d882e",
        "android_client_info": {
          "package_name": "com.digiview.workwell"
        }
      },
      "oauth_client": [],
      "api_key": [
        {
          "current_key": "AIzaSyDpKuQ3vCTJcP-jA9ZrV1N8B1MreBMSR6Q"
        }
      ],
      "services": {
        "appinvite_service": {
          "other_platform_oauth_client": []
        }
      }
    }
  ],
  "configuration_version": "1"
}